Assign 3/half_adder.v

module half_adder(A,B,C,S);

    input A,B;
    output C,S;
    
    assign C = A & B;
    assign S = A ^ B;
    
endmodule

Assign 3/full_adder.v
`include "half_adder.v"
module top(A,B,Cin,Cout,S);

    input A,B,Cin;
    output S,Cout;

    wire W0,W1,W2;


    half_adder u1(.A(A), .B(B), .C(W1), .S(W0));
    half_adder U2(.B(Cin) , .A(W0) , .S(S) , .C(W2));
   
    assign Cout = W1 ^ W2;

endmodule

Assign 3/full_adder_test.v
`include "full_adder.v"
`timescale 10ns/1ns


module full_adder_test;

    //Inputs
    reg A;
    reg B;
    reg Cin;

    //Outputs
    wire S;
    wire Cout;

    //UNIT UNDER TEST
    top UUT(A,B,Cin,S,Cout);

    initial begin
        $dumpfile("full_adder.vcd");
        $dumpvars(0,full_adder_test);
        $display("START OF TEST");
        {A,B,Cin} = 3'b000; #10; $display("%b + %b + %b= %b%b",A,B,Cin,S,Cout);
        {A,B,Cin} = 3'b001; #10; $display("%b + %b + %b= %b%b",A,B,Cin,S,Cout);
        {A,B,Cin} = 3'b010; #10; $display("%b + %b + %b= %b%b",A,B,Cin,S,Cout);
        {A,B,Cin} = 3'b011; #10; $display("%b + %b + %b= %b%b",A,B,Cin,S,Cout);
        {A,B,Cin} = 3'b100; #10; $display("%b + %b + %b= %b%b",A,B,Cin,S,Cout);
        {A,B,Cin} = 3'b101; #10; $display("%b + %b + %b= %b%b",A,B,Cin,S,Cout);
        {A,B,Cin} = 3'b110; #10; $display("%b + %b + %b= %b%b",A,B,Cin,S,Cout);
        {A,B,Cin} = 3'b111; #10; $display("%b + %b + %b= %b%b",A,B,Cin,S,Cout);
        $display("END OF TEST");

 
    end

endmodule

Assign 3/full_adder.vcd
$date
	Mon Feb 15 01:59:03 2021
$end
$version
	Icarus Verilog
$end
$timescale
	1ns
$end
$scope module full_adder_test $end
$var wire 1 ! S $end
$var wire 1 " Cout $end
$var reg 1 # A $end
$var reg 1 $ B $end
$var reg 1 % Cin $end
$scope module UUT $end
$var wire 1 # A $end
$var wire 1 $ B $end
$var wire 1 % Cin $end
$var wire 1 ! Cout $end
$var wire 1 & W2 $end
$var wire 1 ' W1 $end
$var wire 1 ( W0 $end
$var wire 1 " S $end
$scope module U2 $end
$var wire 1 % B $end
$var wire 1 & C $end
$var wire 1 " S $end
$var wire 1 ( A $end
$upscope $end
$scope module u1 $end
$var wire 1 # A $end
$var wire 1 $ B $end
$var wire 1 ' C $end
$var wire 1 ( S $end
$upscope $end
$upscope $end
$upscope $end
$enddefinitions $end
#0
$dumpvars
0(
0'
0&
0%
0$
0#
0"
0!
$end
#100
1"
1%
#200
1(
1"
1$
0%
#300
1!
1&
0"
1%
#400
0!
0&
1"
1#
0$
0%
#500
1!
1&
0"
1%
#600
1'
0(
0&
0"
1$
0%
#700
1"
1%
