Project4/project4.v
module top(A,B,C,D,F);

    input A,B,C,D;
    output F;
    
    assign F = ~A & ~C & D | A & ~C & ~D | B & C & ~D;
    
endmodule

Project4/project4_test.v
`include "project4.v"
`timescale 10ns/1ns

module project4_test;

    reg A, B, C, D;
    wire F;
    top UUT(A, B, C, D, F);
    initial begin
        $dumpfile("project4.vcd");
        $dumpvars(0, project4_test);
        $display("Start of Test");
        {A, B, C, D} = 4'd0; #5; $display("%b %b %b %b | %b", A, B, C, D, F);
        {A, B, C, D} = 4'd1; #5; $display("%b %b %b %b | %b", A, B, C, D, F);
        {A, B, C, D} = 4'd2; #5; $display("%b %b %b %b | %b", A, B, C, D, F);
        {A, B, C, D} = 4'd3; #5; $display("%b %b %b %b | %b", A, B, C, D, F);
        {A, B, C, D} = 4'd4; #5; $display("%b %b %b %b | %b", A, B, C, D, F);
        {A, B, C, D} = 4'd5; #5; $display("%b %b %b %b | %b", A, B, C, D, F);
        {A, B, C, D} = 4'd6; #5; $display("%b %b %b %b | %b", A, B, C, D, F);
        {A, B, C, D} = 4'd7; #5; $display("%b %b %b %b | %b", A, B, C, D, F);
        {A, B, C, D} = 4'd8; #5; $display("%b %b %b %b | %b", A, B, C, D, F);
        {A, B, C, D} = 4'd9; #5; $display("%b %b %b %b | %b", A, B, C, D, F);
        {A, B, C, D} = 4'd10; #5; $display("%b %b %b %b | %b", A, B, C, D, F);
        {A, B, C, D} = 4'd11; #5; $display("%b %b %b %b | %b", A, B, C, D, F);
        {A, B, C, D} = 4'd12; #5; $display("%b %b %b %b | %b", A, B, C, D, F);
        {A, B, C, D} = 4'd13; #5; $display("%b %b %b %b | %b", A, B, C, D, F);
        {A, B, C, D} = 4'd14; #5; $display("%b %b %b %b | %b", A, B, C, D, F);
        {A, B, C, D} = 4'd15; #5; $display("%b %b %b %b | %b", A, B, C, D, F);
        $display("End of Test");
    end
endmodule

Project4/project4.vcd
$date
	Sun Mar 07 21:35:17 2021
$end
$version
	Icarus Verilog
$end
$timescale
	1ns
$end
$scope module project4_test $end
$var wire 1 ! F $end
$var reg 1 " A $end
$var reg 1 # B $end
$var reg 1 $ C $end
$var reg 1 % D $end
$scope module UUT $end
$var wire 1 " A $end
$var wire 1 # B $end
$var wire 1 $ C $end
$var wire 1 % D $end
$var wire 1 ! F $end
$upscope $end
$upscope $end
$enddefinitions $end
#0
$dumpvars
0%
0$
0#
0"
0!
$end
#50
1!
1%
#100
0!
1$
0%
#150
1%
#200
1#
0$
0%
#250
1!
1%
#300
1$
0%
#350
0!
1%
#400
1!
1"
0#
0$
0%
#450
0!
1%
#500
0!
1$
0%
#550
1%
#600
1!
1#
0$
0%
#650
0!
1%
#700
1!
1$
0%
#750
0!
1%
