Assign 3/half_adder.v

module half_adder(A,B,C,S);

    input A,B;
    output C,S;
    
    assign C = A & B;
    assign S = A ^ B;
    
endmodule

ALU/full_adder.v
`include "half_adder.v"
module full_adder(A, B, Cin, Cout, S);
    input A, B, Cin;
    output Cout, S;
    wire C0, S0, C1;
    half_adder HA0(.A(A), .B(B), .C(C0), .S(S0));
    half_adder HA1(.A(S0), .B(Cin), .C(C1), .S(S));
    assign Cout = C0 ^ C1;
endmodule

ALU/full_adder_test.v
`include "full_adder.v"
`timescale 1ps/1ps

module full_adder_test;
    reg A, B, Cin;
    wire Cout, S;
    full_adder UUT(A, B, Cin, Cout, S);
    initial begin
        $dumpfile("full_adder.vcd");
        $dumpvars(0, full_adder_test);
        $display("Start of Test");
        {A, B, Cin} = 3'd0; #5; $display("%b + %b + %b = %b%b", A, B, Cin, Cout, S);
        {A, B, Cin} = 3'd1; #5; $display("%b + %b + %b = %b%b", A, B, Cin, Cout, S);
        {A, B, Cin} = 3'd2; #5; $display("%b + %b + %b = %b%b", A, B, Cin, Cout, S);
        {A, B, Cin} = 3'd3; #5; $display("%b + %b + %b = %b%b", A, B, Cin, Cout, S);
        {A, B, Cin} = 3'd4; #5; $display("%b + %b + %b = %b%b", A, B, Cin, Cout, S);
        {A, B, Cin} = 3'd5; #5; $display("%b + %b + %b = %b%b", A, B, Cin, Cout, S);
        {A, B, Cin} = 3'd6; #5; $display("%b + %b + %b = %b%b", A, B, Cin, Cout, S);
        {A, B, Cin} = 3'd7; #5; $display("%b + %b + %b = %b%b", A, B, Cin, Cout, S);
        $display("End of Test");
    end
endmodule

ALU/full_adder.vcd
$date
	Mon Mar 29 03:35:19 2021
$end
$version
	Icarus Verilog
$end
$timescale
	1ps
$end
$scope module full_adder_test $end
$var wire 1 ! S $end
$var wire 1 " Cout $end
$var reg 1 # A $end
$var reg 1 $ B $end
$var reg 1 % Cin $end
$scope module UUT $end
$var wire 1 # A $end
$var wire 1 $ B $end
$var wire 1 % Cin $end
$var wire 1 " Cout $end
$var wire 1 & S0 $end
$var wire 1 ! S $end
$var wire 1 ' C1 $end
$var wire 1 ( C0 $end
$scope module HA0 $end
$var wire 1 # A $end
$var wire 1 $ B $end
$var wire 1 ( C $end
$var wire 1 & S $end
$upscope $end
$scope module HA1 $end
$var wire 1 & A $end
$var wire 1 % B $end
$var wire 1 ' C $end
$var wire 1 ! S $end
$upscope $end
$upscope $end
$upscope $end
$enddefinitions $end
#0
$dumpvars
0(
0'
0&
0%
0$
0#
0"
0!
$end
#5
1!
1%
#10
1&
1!
1$
0%
#15
1"
1'
0!
1%
#20
0"
0'
1!
1#
0$
0%
#25
1"
1'
0!
1%
#30
1(
0&
0'
0!
1$
0%
#35
1!
1%
